fpml/__init__.py
fpml/core/__init__.py
fpml/core/constants.py
fpml/core/core_exceptions.py
fpml/core/core_types.py
fpml/core/extract.py
fpml/core/guarded_resource.py
fpml/core/utils.py
fpml-0.2.0.dist-info/METADATA
fpml-0.2.0.dist-info/WHEEL
fpml-0.2.0.dist-info/RECORD
